autoremovetorrents/__init__.py
autoremovetorrents/clientstatus.py
autoremovetorrents/conditionlexer.py
autoremovetorrents/conditionparser.py
autoremovetorrents/lextab.py
autoremovetorrents/logger.py
autoremovetorrents/main.py
autoremovetorrents/parser.out
autoremovetorrents/parsetab.py
autoremovetorrents/strategy.py
autoremovetorrents/task.py
autoremovetorrents/torrent.py
autoremovetorrents/torrentstatus.py
autoremovetorrents/version.py
autoremovetorrents/__pycache__/__init__.cpython-311.pyc
autoremovetorrents/__pycache__/clientstatus.cpython-311.pyc
autoremovetorrents/__pycache__/conditionlexer.cpython-311.pyc
autoremovetorrents/__pycache__/conditionparser.cpython-311.pyc
autoremovetorrents/__pycache__/logger.cpython-311.pyc
autoremovetorrents/__pycache__/main.cpython-311.pyc
autoremovetorrents/__pycache__/parsetab.cpython-311.pyc
autoremovetorrents/__pycache__/strategy.cpython-311.pyc
autoremovetorrents/__pycache__/task.cpython-311.pyc
autoremovetorrents/__pycache__/torrent.cpython-311.pyc
autoremovetorrents/__pycache__/torrentstatus.cpython-311.pyc
autoremovetorrents/__pycache__/version.cpython-311.pyc
autoremovetorrents/client/__init__.py
autoremovetorrents/client/deluge.py
autoremovetorrents/client/hnr_api.py
autoremovetorrents/client/qbittorrent.py
autoremovetorrents/client/transmission.py
autoremovetorrents/client/utorrent.py
autoremovetorrents/client/__pycache__/__init__.cpython-311.pyc
autoremovetorrents/client/__pycache__/deluge.cpython-311.pyc
autoremovetorrents/client/__pycache__/hnr_api.cpython-311.pyc
autoremovetorrents/client/__pycache__/qbittorrent.cpython-311.pyc
autoremovetorrents/client/__pycache__/transmission.cpython-311.pyc
autoremovetorrents/client/__pycache__/utorrent.cpython-311.pyc
autoremovetorrents/compatibility/__init__.py
autoremovetorrents/compatibility/disk_usage_.py
autoremovetorrents/compatibility/inf_.py
autoremovetorrents/compatibility/open_.py
autoremovetorrents/compatibility/pyyaml_version_.py
autoremove_torrents_hnr-2.0.0.dist-info/LICENSE
autoremove_torrents_hnr-2.0.0.dist-info/METADATA
autoremove_torrents_hnr-2.0.0.dist-info/WHEEL
autoremove_torrents_hnr-2.0.0.dist-info/entry_points.txt
autoremove_torrents_hnr-2.0.0.dist-info/top_level.txt
autoremove_torrents_hnr-2.0.0.dist-info/zip-safe
autoremove_torrents_hnr-2.0.0.dist-info/RECORD
