Metadata-Version: 2.1
Name: autoremove-torrents-hnr
Version: 2.0.0
Summary: Automatically remove torrents according to your strategies with H&R check support.
Home-page: https://github.com/tjupt/autoremove-torrents
Author: TJUPT
Author-email: ptmaster@tjupt.org
License: MIT
Keywords: python autoremove torrent
Classifier: Environment :: Console
Classifier: License :: OSI Approved :: MIT License
Classifier: Programming Language :: Python
Classifier: Topic :: Utilities
License-File: LICENSE
Requires-Dist: deluge-client
Requires-Dist: enum34
Requires-Dist: ply
Requires-Dist: pyyaml
Requires-Dist: requests
